hydroffice.soundspeed-2017.0.0-py2.7-nspkg.pth
hydroffice/sis/__init__.py
hydroffice/sis/__main__.py
hydroffice/sis/controlpanel.py
hydroffice/sis/kmbase.py
hydroffice/sis/mainwin.py
hydroffice/sis/process.py
hydroffice/sis/replaythread.py
hydroffice/sis/run.py
hydroffice/sis/svpthread.py
hydroffice/soundspeed/__init__.py
hydroffice/soundspeed/soundspeed.py
hydroffice/soundspeed/appdirs/__init__.py
hydroffice/soundspeed/appdirs/appdirs.py
hydroffice/soundspeed/atlas/__init__.py
hydroffice/soundspeed/atlas/abstract.py
hydroffice/soundspeed/atlas/atlases.py
hydroffice/soundspeed/atlas/ftp.py
hydroffice/soundspeed/atlas/rtofs/__init__.py
hydroffice/soundspeed/atlas/rtofs/rtofs.py
hydroffice/soundspeed/atlas/woa09/__init__.py
hydroffice/soundspeed/atlas/woa09/woa09.py
hydroffice/soundspeed/atlas/woa13/__init__.py
hydroffice/soundspeed/atlas/woa13/woa13.py
hydroffice/soundspeed/base/__init__.py
hydroffice/soundspeed/base/basedb.py
hydroffice/soundspeed/base/gdal_aux.py
hydroffice/soundspeed/base/geodesy.py
hydroffice/soundspeed/base/helper.py
hydroffice/soundspeed/base/setup.py
hydroffice/soundspeed/base/setup_db.py
hydroffice/soundspeed/base/setup_sql.py
hydroffice/soundspeed/base/testing.py
hydroffice/soundspeed/base/callbacks/__init__.py
hydroffice/soundspeed/base/callbacks/abstract_callbacks.py
hydroffice/soundspeed/base/callbacks/cli_callbacks.py
hydroffice/soundspeed/base/callbacks/test_callbacks.py
hydroffice/soundspeed/base/progress/__init__.py
hydroffice/soundspeed/base/progress/abstract_progress.py
hydroffice/soundspeed/base/progress/cli_progress.py
hydroffice/soundspeed/client/__init__.py
hydroffice/soundspeed/client/client.py
hydroffice/soundspeed/client/clientlist.py
hydroffice/soundspeed/db/__init__.py
hydroffice/soundspeed/db/db.py
hydroffice/soundspeed/db/export.py
hydroffice/soundspeed/db/plot.py
hydroffice/soundspeed/db/point.py
hydroffice/soundspeed/formats/__init__.py
hydroffice.soundspeed-2017.0.0.dist-info/DESCRIPTION.rst
hydroffice.soundspeed-2017.0.0.dist-info/METADATA
hydroffice.soundspeed-2017.0.0.dist-info/RECORD
hydroffice.soundspeed-2017.0.0.dist-info/WHEEL
hydroffice.soundspeed-2017.0.0.dist-info/entry_points.txt
hydroffice.soundspeed-2017.0.0.dist-info/metadata.json
hydroffice.soundspeed-2017.0.0.dist-info/namespace_packages.txt
hydroffice.soundspeed-2017.0.0.dist-info/pbr.json
hydroffice.soundspeed-2017.0.0.dist-info/top_level.txt
