Metadata-Version: 2.0
Name: hydroffice.soundspeed
Version: 2017.0.0
Summary: A library and an application to manage sound speed profiles.
Home-page: https://bitbucket.org/ccomjhc/hyo_soundspeed/
Author: Giuseppe Masetti(UNH,CCOM); Barry Gallagher(NOAA, OCS); Brian Calder(UNH,CCOM); Chen Zhang(NOAA,OCS); Matt Wilson(NOAA,OCS);  Jack Riley(NOAA,OCS)
Author-email: gmasetti@ccom.unh.edu; barry.gallagher@noaa.gov; brc@ccom.unh.edu; chen.zhang@noaa.gov; matthew.wilson@noaa.gov; jack.riley@noaa.gov
License: LGPLv2.1 or CCOM-UNH Industrial Associate license
Keywords: hydrography ocean mapping survey sound speed profiles
Platform: UNKNOWN
Classifier: Development Status :: 4 - Beta
Classifier: Intended Audience :: Science/Research
Classifier: Natural Language :: English
Classifier: License :: OSI Approved :: GNU Lesser General Public License v3 (LGPLv3)
Classifier: Operating System :: OS Independent
Classifier: Programming Language :: Python
Classifier: Programming Language :: Python :: 2
Classifier: Programming Language :: Python :: 2.7
Classifier: Programming Language :: Python :: 3
Classifier: Programming Language :: Python :: 3.4
Classifier: Topic :: Scientific/Engineering :: GIS
Classifier: Topic :: Office/Business :: Office Suites
Requires-Dist: basemap
Requires-Dist: gdal
Requires-Dist: gsw
Requires-Dist: matplotlib
Requires-Dist: netCDF4
Requires-Dist: numpy
Requires-Dist: pillow
Requires-Dist: pyproj
Requires-Dist: pyserial
Requires-Dist: pyside
